wavy/__init__.py
wavy/models.py
wavy/panel.py
wavy/plot.py
wavy/validations.py
wavyts-0.1.10.dist-info/LICENSE.txt
wavyts-0.1.10.dist-info/WHEEL
wavyts-0.1.10.dist-info/METADATA
wavyts-0.1.10.dist-info/RECORD
