Metadata-Version: 2.1
Name: wavyts
Version: 0.1.10
Summary: Wavy is a library to facilitate time series analysis
Home-page: https://github.com/logspace-ai/wavy
License: MIT
Author: Ibis Prevedello
Author-email: ibiscp@gmail.com
Requires-Python: >=3.8,<3.11
Classifier: License :: OSI Approved :: MIT License
Classifier: Programming Language :: Python :: 3
Classifier: Programming Language :: Python :: 3.8
Classifier: Programming Language :: Python :: 3.9
Classifier: Programming Language :: Python :: 3.10
Requires-Dist: ipykernel (>=6.15.1,<7.0.0)
Requires-Dist: nbformat (>=5.4.0,<6.0.0)
Requires-Dist: numpy (>=1.22.3,<2.0.0)
Requires-Dist: pandas (==1.4.3)
Requires-Dist: plotlab (>=0.1.0,<0.2.0)
Requires-Dist: plotly (>=5.7.0,<6.0.0)
Requires-Dist: sklearn (>=0.0,<0.1)
Requires-Dist: tensorflow (>=2.8.0,<3.0.0)
Requires-Dist: toml (>=0.10.2,<0.11.0)
Requires-Dist: tqdm (>=4.64.0,<5.0.0)
Project-URL: Repository, https://github.com/logspace-ai/wavy
